syncmaster_commons/__init__.py
syncmaster_commons/keys.py
syncmaster_commons/task_names.py
syncmaster_commons/abstract/__init__.py
syncmaster_commons/abstract/baseclass.py
syncmaster_commons/abstract/enforcers.py
syncmaster_commons/agents/__init__.py
syncmaster_commons/agents/request_payload.py
syncmaster_commons/agents/response_payload.py
syncmaster_commons/gupshup/__init__.py
syncmaster_commons/gupshup/abstracts.py
syncmaster_commons/gupshup/agent_request_payload.py
syncmaster_commons/gupshup/agent_response_payload.py
syncmaster_commons/gupshup/atomic_incoming_payload.py
syncmaster_commons/gupshup/incoming_payloads.py
syncmaster_commons/gupshup/outgoing_payloads.py
syncmaster_commons/translator/__init__.py
syncmaster_commons/translator/base.py
syncmaster_commons/translator/parsers.py
syncmaster_commons/translator/prompt.py
tests/__init__.py
tests/test_incoming_payload.py
tests/test_outgoing_payload.py
tests/test_translator.py
syncmaster_commons-0.0.44.dist-info/LICENSE
syncmaster_commons-0.0.44.dist-info/METADATA
syncmaster_commons-0.0.44.dist-info/WHEEL
syncmaster_commons-0.0.44.dist-info/top_level.txt
syncmaster_commons-0.0.44.dist-info/RECORD
