Metadata-Version: 2.1
Name: syncmaster-commons
Version: 0.0.44
Summary: A core library for syncmaster.
Home-page: https://github.com/jain-t/syncmaster-commons
Author: jain-t, nakulben
Author-email: tech@jinacode.systems
Classifier: Programming Language :: Python :: 3
Classifier: License :: OSI Approved :: MIT License
Classifier: Operating System :: OS Independent
Requires-Python: >=3.6
License-File: LICENSE
Requires-Dist: pydantic
Requires-Dist: setuptools
Requires-Dist: pytest
Requires-Dist: langchain
Requires-Dist: langchain-openai
Requires-Dist: python-dotenv
